odoo/addons/l10n_es_aeat_mod303/README.rst
odoo/addons/l10n_es_aeat_mod303/__init__.py
odoo/addons/l10n_es_aeat_mod303/__manifest__.py
odoo/addons/l10n_es_aeat_mod303/data/aeat_export_mod303_2018_data.xml
odoo/addons/l10n_es_aeat_mod303/data/aeat_export_mod303_2021_data.xml
odoo/addons/l10n_es_aeat_mod303/data/l10n.es.aeat.mod303.report.activity.code.csv
odoo/addons/l10n_es_aeat_mod303/data/tax_code_map_mod303_data.xml
odoo/addons/l10n_es_aeat_mod303/data/2021-07/aeat.model.export.config.csv
odoo/addons/l10n_es_aeat_mod303/data/2021-07/aeat.model.export.config.line.csv
odoo/addons/l10n_es_aeat_mod303/data/2021-07/l10n.es.aeat.map.tax.csv
odoo/addons/l10n_es_aeat_mod303/data/2021-07/l10n.es.aeat.map.tax.line.csv
odoo/addons/l10n_es_aeat_mod303/data/2022/aeat.model.export.config.csv
odoo/addons/l10n_es_aeat_mod303/data/2022/aeat.model.export.config.line.csv
odoo/addons/l10n_es_aeat_mod303/data/2023/aeat.model.export.config.csv
odoo/addons/l10n_es_aeat_mod303/data/2023/aeat.model.export.config.line.csv
odoo/addons/l10n_es_aeat_mod303/data/2023/l10n.es.aeat.map.tax.csv
odoo/addons/l10n_es_aeat_mod303/data/2023/l10n.es.aeat.map.tax.line.csv
odoo/addons/l10n_es_aeat_mod303/data/2024-10/aeat.model.export.config.csv
odoo/addons/l10n_es_aeat_mod303/data/2024-10/aeat.model.export.config.line.csv
odoo/addons/l10n_es_aeat_mod303/data/2024-10/l10n.es.aeat.map.tax.csv
odoo/addons/l10n_es_aeat_mod303/data/2024-10/l10n.es.aeat.map.tax.line.csv
odoo/addons/l10n_es_aeat_mod303/docs/DR303e23.xlsx
odoo/addons/l10n_es_aeat_mod303/docs/DR303e24v200.xlsx
odoo/addons/l10n_es_aeat_mod303/docs/DR303e25v101.xlsx
odoo/addons/l10n_es_aeat_mod303/i18n/bg.po
odoo/addons/l10n_es_aeat_mod303/i18n/ca.po
odoo/addons/l10n_es_aeat_mod303/i18n/cs.po
odoo/addons/l10n_es_aeat_mod303/i18n/de.po
odoo/addons/l10n_es_aeat_mod303/i18n/es.po
odoo/addons/l10n_es_aeat_mod303/i18n/es_CO.po
odoo/addons/l10n_es_aeat_mod303/i18n/es_CR.po
odoo/addons/l10n_es_aeat_mod303/i18n/eu.po
odoo14_addon_l10n_es_aeat_mod303-14.0.5.1.0.dist-info/METADATA
odoo14_addon_l10n_es_aeat_mod303-14.0.5.1.0.dist-info/WHEEL
odoo14_addon_l10n_es_aeat_mod303-14.0.5.1.0.dist-info/top_level.txt
odoo14_addon_l10n_es_aeat_mod303-14.0.5.1.0.dist-info/RECORD
