Metadata-Version: 2.1
Name: odoo14-addon-l10n_es_aeat_mod303
Version: 14.0.5.1.0
Summary: AEAT modelo 303
Home-page: https://github.com/OCA/l10n-spain
Author: Guadaltech,AvanzOSC,Tecnativa,ForgeFlow,Odoo Community Association (OCA)
Author-email: support@odoo-community.org
License: AGPL-3
Classifier: Programming Language :: Python
Classifier: Framework :: Odoo
Classifier: Framework :: Odoo :: 14.0
Classifier: License :: OSI Approved :: GNU Affero General Public License v3
Requires-Python: >=3.6
Requires-Dist: odoo14-addon-l10n-es-aeat
Requires-Dist: odoo14-addon-l10n-es-extra-data
Requires-Dist: odoo<14.1dev,>=14.0a
